PKG-INFO
README.txt
setup.cfg
setup.py
anz/__init__.py
anz.dashboard.egg-info/PKG-INFO
anz.dashboard.egg-info/SOURCES.txt
anz.dashboard.egg-info/dependency_links.txt
anz.dashboard.egg-info/entry_points.txt
anz.dashboard.egg-info/namespace_packages.txt
anz.dashboard.egg-info/not-zip-safe
anz.dashboard.egg-info/paster_plugins.txt
anz.dashboard.egg-info/requires.txt
anz.dashboard.egg-info/top_level.txt
anz/dashboard/__init__.py
anz/dashboard/config.py
anz/dashboard/configure.zcml
anz/dashboard/dashboard.py
anz/dashboard/interfaces.py
anz/dashboard/browser/__init__.py
anz/dashboard/browser/calendarwidgetview.py
anz/dashboard/browser/configure.zcml
anz/dashboard/browser/dashboardview.py
anz/dashboard/browser/foldercontentswidgetview.py
anz/dashboard/browser/mergedrequestview.py
anz/dashboard/browser/messagecatalogview.py
anz/dashboard/browser/rsswidgetview.py
anz/dashboard/browser/templates.zcml
anz/dashboard/browser/weatherwidgetview.py
anz/dashboard/browser/widgetview.py
anz/dashboard/browser/templates/dashboardlayout.pt
anz/dashboard/browser/templates/dashboardview.pt
anz/dashboard/i18n/anz.dashboard-plone-zh-cn.po
anz/dashboard/locales/zh-cn/LC_MESSAGES/anz.dashboard.mo
anz/dashboard/locales/zh-cn/LC_MESSAGES/anz.dashboard.po
anz/dashboard/profiles/default/actions.xml
anz/dashboard/profiles/default/factorytool.xml
anz/dashboard/profiles/default/propertiestool.xml
anz/dashboard/profiles/default/skins.xml
anz/dashboard/profiles/default/types.xml
anz/dashboard/profiles/default/types/Anz_Dashboard.xml
anz/dashboard/skins/anz_dashboard/MultiSelect.js
anz/dashboard/skins/anz_dashboard/Portal.js
anz/dashboard/skins/anz_dashboard/PortalColumn.js
anz/dashboard/skins/anz_dashboard/TabMoreMenu.css
anz/dashboard/skins/anz_dashboard/TabMoreMenu.js
anz/dashboard/skins/anz_dashboard/TreeComboSuperBox.css
anz/dashboard/skins/anz_dashboard/TreeComboSuperBox.js
anz/dashboard/skins/anz_dashboard/XCheckbox.js
anz/dashboard/skins/anz_dashboard/anz.dashboard.layout-min.css
anz/dashboard/skins/anz_dashboard/anz.dashboard.layout-min.js
anz/dashboard/skins/anz_dashboard/anz.dashboard.view-min.css
anz/dashboard/skins/anz_dashboard/anz.dashboard.view-min.js
anz/dashboard/skins/anz_dashboard/anz_dashboard.css
anz/dashboard/skins/anz_dashboard/anz_dashboard.js
anz/dashboard/skins/anz_dashboard/anz_dashboard_view.js
