Metadata-Version: 1.0
Name: anz.dashboard
Version: 0.61
Summary: Plone netvibes like dashboard implementation
Home-page: http://plone.org/products/anz.dashboard/
Author: jiangdongjin
Author-email: eastxing@gmail.com
License: GPL
Keywords: plone anz dashboard
Platform: UNKNOWN
Classifier: Framework :: Plone
Classifier: Programming Language :: Python
